opcua_data_diode/__init__.py
opcua_data_diode/cli/__init__.py
opcua_data_diode/cli/receiver_auto.py
opcua_data_diode/cli/sender_auto.py
opcua_data_diode/gui/__init__.py
opcua_data_diode/gui/green.png
opcua_data_diode/gui/receiver_gui.py
opcua_data_diode/gui/receiver_gui_ncurses.py
opcua_data_diode/gui/red.png
opcua_data_diode/gui/sender_gui.py
opcua_data_diode/gui/sender_gui_ncurses.py
opcua_data_diode-1.0.4.dist-info/licenses/LICENSE
opcua_data_diode-1.0.4.dist-info/METADATA
opcua_data_diode-1.0.4.dist-info/WHEEL
opcua_data_diode-1.0.4.dist-info/entry_points.txt
opcua_data_diode-1.0.4.dist-info/top_level.txt
opcua_data_diode-1.0.4.dist-info/RECORD
