Metadata-Version: 2.4
Name: opcua-data-diode
Version: 1.0.4
Summary: Secure one-way data replication for OPC UA servers using UDP over hardware data diodes
Home-page: https://github.com/cherubimro/opcua-data-diode
Author: Alin-Adrian Anton
Author-email: Alin-Adrian Anton <alin.anton@upt.ro>
License: GPL-3.0-or-later
Project-URL: Homepage, https://github.com/cherubimro/opcua-data-diode
Project-URL: Documentation, https://github.com/cherubimro/opcua-data-diode/tree/main/docs
Project-URL: Repository, https://github.com/cherubimro/opcua-data-diode
Project-URL: Issues, https://github.com/cherubimro/opcua-data-diode/issues
Keywords: opcua,data-diode,security,scada,ot,industrial,cybersecurity
Classifier: Development Status :: 4 - Beta
Classifier: Intended Audience :: Manufacturing
Classifier: License :: OSI Approved :: GNU General Public License v3 (GPLv3)
Classifier: Programming Language :: Python :: 3
Requires-Python: >=3.7
License-File: LICENSE
Requires-Dist: asyncua>=1.1.5
Requires-Dist: lz4
Requires-Dist: cryptography
Requires-Dist: Pillow
Requires-Dist: pyperclip
Provides-Extra: dev
Requires-Dist: pytest>=6.0; extra == "dev"
Requires-Dist: pytest-asyncio; extra == "dev"
Requires-Dist: pytest-cov; extra == "dev"
Requires-Dist: black; extra == "dev"
Requires-Dist: flake8; extra == "dev"
Requires-Dist: mypy; extra == "dev"
Provides-Extra: docs
Requires-Dist: sphinx; extra == "docs"
Requires-Dist: sphinx-rtd-theme; extra == "docs"
Dynamic: author
Dynamic: home-page
Dynamic: license-file
Dynamic: requires-python
